MANIFEST.in
README.md
setup.py
helix/__init__.py
helix/clock.py
helix/components.py
helix/defines.py
helix/events.py
helix/gui.py
helix/light.py
helix/math.py
helix/physics.py
helix/resource.py
helix/version.py
helix/assets/cursor.png
helix/assets/helix-pride.png
helix_beta.egg-info/PKG-INFO
helix_beta.egg-info/SOURCES.txt
helix_beta.egg-info/dependency_links.txt
helix_beta.egg-info/requires.txt
helix_beta.egg-info/top_level.txt